Metadata-Version: 1.1
Name: django-zebra
Version: 0.4.5
Summary: Library for Django and Stripe
Home-page: https://github.com/GoodCloud/django-zebra
Author: Steven Skoczen
Author-email: steven@agoodcloud.com
License: UNKNOWN
Platform: UNKNOWN
Classifier: Programming Language :: Python
Classifier: License :: OSI Approved :: MIT License
Classifier: Operating System :: OS Independent
Classifier: Development Status :: 4 - Beta
Classifier: Environment :: Web Environment
Classifier: Framework :: Django
Classifier: Intended Audience :: Developers
Classifier: Topic :: Internet :: WWW/HTTP
Classifier: Topic :: Software Development :: Libraries :: Python Modules
